test_bed_adapter/__init__.py
test_bed_adapter/kafka/__init__.py
test_bed_adapter/kafka/consumer_manager.py
test_bed_adapter/kafka/heartbeat_manager.py
test_bed_adapter/kafka/kafka_manager.py
test_bed_adapter/kafka/producer_manager.py
test_bed_adapter/options/__init__.py
test_bed_adapter/options/test_bed_options.py
test_bed_adapter/registry/__init__.py
test_bed_adapter/registry/schema_access.py
test_bed_adapter/registry/schema_publisher.py
test_bed_adapter/registry/schema_registry.py
test_bed_adapter/utils/__init__.py
test_bed_adapter/utils/avro_schema_helper.py
test_bed_adapter/utils/event_hook.py
test_bed_adapter/utils/helpers.py
tests/__init__.py
tests/test_bed_adapter_consumer_changing_id.py
tests/test_bed_adapter_consumer_kafka.py
tests/test_bed_adapter_consumer_kafka_timer.py
tests/test_bed_adapter_producer_kafka.py
tests/test_heartbeat_timer.py
tests/test_schema_publisher.py
tests/test_schema_registry.py
python_test_bed_adapter-0.0.6.dist-info/LICENSE
python_test_bed_adapter-0.0.6.dist-info/METADATA
python_test_bed_adapter-0.0.6.dist-info/WHEEL
python_test_bed_adapter-0.0.6.dist-info/top_level.txt
python_test_bed_adapter-0.0.6.dist-info/RECORD
