Metadata-Version: 2.1
Name: python-test-bed-adapter
Version: 0.0.6
Summary: This is the test-bed adapter for Python: it allows you to easily connect Python services to the Apache Kafka test-bed via Python.
Home-page: https://github.com/DRIVER-EU/python-test-bed-adapter
Author: Hugo J. Bello
Author-email: hjbello.wk@gmail.com
License: UNKNOWN
Platform: UNKNOWN
Classifier: Programming Language :: Python :: 3
Classifier: License :: OSI Approved :: MIT License
Classifier: Operating System :: OS Independent
